opengai/__init__.py
opengai-0.0.0a0.dist-info/LICENSE
opengai-0.0.0a0.dist-info/METADATA
opengai-0.0.0a0.dist-info/WHEEL
opengai-0.0.0a0.dist-info/top_level.txt
opengai-0.0.0a0.dist-info/RECORD
